exhale/__init__.py
exhale/configs.py
exhale/deploy.py
exhale/graph.py
exhale/parse.py
exhale/utils.py
exhale/data/treeView/collapsible-lists/LICENSE.md
exhale/data/treeView/collapsible-lists/css/button-closed.png
exhale/data/treeView/collapsible-lists/css/button-open.png
exhale/data/treeView/collapsible-lists/css/button.png
exhale/data/treeView/collapsible-lists/css/list-item-contents.png
exhale/data/treeView/collapsible-lists/css/list-item-last-open.png
exhale/data/treeView/collapsible-lists/css/list-item-last.png
exhale/data/treeView/collapsible-lists/css/list-item-open.png
exhale/data/treeView/collapsible-lists/css/list-item-root.png
exhale/data/treeView/collapsible-lists/css/list-item.png
exhale/data/treeView/collapsible-lists/css/tree_view.css
exhale/data/treeView/collapsible-lists/js/CollapsibleLists.compressed.js
exhale/data/treeView/collapsible-lists/js/apply-collapsible-lists.js
exhale/data/treeView-bootstrap/bootstrap-treeview/LICENSE
exhale/data/treeView-bootstrap/bootstrap-treeview/apply-bootstrap-treview.js
exhale/data/treeView-bootstrap/bootstrap-treeview/bootstrap-treeview.min.css
exhale/data/treeView-bootstrap/bootstrap-treeview/bootstrap-treeview.min.js
exhale-0.3.7.dist-info/LICENSE
exhale-0.3.7.dist-info/METADATA
exhale-0.3.7.dist-info/WHEEL
exhale-0.3.7.dist-info/top_level.txt
exhale-0.3.7.dist-info/RECORD
