Metadata-Version: 2.1
Name: exhale
Version: 0.3.7
Summary: Automatic C++ library API documentation generator using Doxygen, Sphinx, and
Home-page: https://github.com/svenevs/exhale
Author: Stephen McDowell
Author-email: svenevs.pypi@gmail.com
License: BSD 3-Clause License
Project-URL: Documentation, https://exhale.readthedocs.io/en/latest/
Project-URL: Source, https://github.com/svenevs/exhale
Project-URL: Tracker, https://github.com/svenevs/exhale/issues
Classifier: Development Status :: 3 - Alpha
Classifier: Framework :: Sphinx :: Extension
Classifier: Intended Audience :: Developers
Classifier: License :: OSI Approved :: BSD License
Classifier: Natural Language :: English
Classifier: Programming Language :: Python
Classifier: Programming Language :: Python :: 3
Classifier: Programming Language :: Python :: 3.8
Classifier: Programming Language :: Python :: 3.9
Classifier: Programming Language :: Python :: 3.10
Classifier: Programming Language :: Python :: 3.11
Classifier: Programming Language :: Python :: 3.12
Classifier: Topic :: Documentation :: Sphinx
Classifier: Topic :: Software Development :: Documentation
Requires-Python: >=3.8
License-File: LICENSE
Requires-Dist: breathe >=4.33.1
Requires-Dist: Sphinx >=4.3.2
Requires-Dist: beautifulsoup4
Requires-Dist: lxml
Requires-Dist: six
